MANIFEST.in
setup.py
code2/__init__.py
code2/cli.py
code2/context.py
code2/db.py
code2/diff.py
code2/markdown.py
code2/orm.py
code2/project.py
code2/prompt2.py
code2/scan.py
code2/workflow.py
code2.egg-info/PKG-INFO
code2.egg-info/SOURCES.txt
code2.egg-info/dependency_links.txt
code2.egg-info/entry_points.txt
code2.egg-info/requires.txt
code2.egg-info/top_level.txt
code2/workflows/__init__.py
code2/workflows/analyze.py
code2/workflows/ask.py
code2/workflows/cmd.py
code2/workflows/create.py
code2/workflows/edit.py
code2/workflows/hack.py